{
  "title": "Node Overview",
  "uid": "node-overview",
  "tags": ["nodes", "node-exporter"],
  "schemaVersion": 40,
  "version": 2,
  "refresh": "1m",
  "time": { "from": "now-3h", "to": "now" },
  "timezone": "browser",
  "editable": true,
  "graphTooltip": 1,
  "templating": {
    "list": [
      {
        "name": "instance",
        "label": "Host",
        "type": "query",
        "datasource": { "type": "prometheus", "uid": "prometheus" },
        "query": "label_values(node_cpu_seconds_total{job=\"node_exporter\"}, instance)",
        "refresh": 2,
        "sort": 1,
        "includeAll": false,
        "multi": false,
        "current": {}
      }
    ]
  },
  "panels": [
    {
      "id": 1,
      "title": "CPU Utilization",
      "type": "timeseries",
      "gridPos": { "h": 8, "w": 12, "x": 0, "y": 0 },
      "datasource": { "type": "prometheus", "uid": "prometheus" },
      "targets": [
        {
          "datasource": { "type": "prometheus", "uid": "prometheus" },
          "expr": "1 - avg without(cpu, mode)(rate(node_cpu_seconds_total{job=\"node_exporter\", mode=\"idle\", instance=~\"$instance\"}[5m]))",
          "legendFormat": "cpu used",
          "refId": "A"
        }
      ],
      "fieldConfig": {
        "defaults": {
          "unit": "percentunit",
          "min": 0,
          "max": 1,
          "color": { "mode": "palette-classic" }
        },
        "overrides": []
      },
      "options": {
        "tooltip": { "mode": "single", "sort": "none" },
        "legend": { "displayMode": "list", "placement": "bottom", "showLegend": true }
      }
    },
    {
      "id": 2,
      "title": "Load per CPU",
      "type": "timeseries",
      "gridPos": { "h": 8, "w": 12, "x": 12, "y": 0 },
      "datasource": { "type": "prometheus", "uid": "prometheus" },
      "targets": [
        {
          "datasource": { "type": "prometheus", "uid": "prometheus" },
          "expr": "node_load1{job=\"node_exporter\", instance=~\"$instance\"} / count without(cpu)(count without(mode)(node_cpu_seconds_total{job=\"node_exporter\", instance=~\"$instance\"}))",
          "legendFormat": "load1 / cpu",
          "refId": "A"
        },
        {
          "datasource": { "type": "prometheus", "uid": "prometheus" },
          "expr": "node_load5{job=\"node_exporter\", instance=~\"$instance\"} / count without(cpu)(count without(mode)(node_cpu_seconds_total{job=\"node_exporter\", instance=~\"$instance\"}))",
          "legendFormat": "load5 / cpu",
          "refId": "B"
        },
        {
          "datasource": { "type": "prometheus", "uid": "prometheus" },
          "expr": "node_load15{job=\"node_exporter\", instance=~\"$instance\"} / count without(cpu)(count without(mode)(node_cpu_seconds_total{job=\"node_exporter\", instance=~\"$instance\"}))",
          "legendFormat": "load15 / cpu",
          "refId": "C"
        }
      ],
      "fieldConfig": {
        "defaults": {
          "unit": "short",
          "min": 0,
          "color": { "mode": "palette-classic" }
        },
        "overrides": []
      },
      "options": {
        "tooltip": { "mode": "single", "sort": "none" },
        "legend": { "displayMode": "list", "placement": "bottom", "showLegend": true }
      }
    },
    {
      "id": 3,
      "title": "Memory Utilization",
      "type": "timeseries",
      "gridPos": { "h": 8, "w": 12, "x": 0, "y": 8 },
      "datasource": { "type": "prometheus", "uid": "prometheus" },
      "targets": [
        {
          "datasource": { "type": "prometheus", "uid": "prometheus" },
          "expr": "1 - (node_memory_MemAvailable_bytes{job=\"node_exporter\", instance=~\"$instance\"} / node_memory_MemTotal_bytes{job=\"node_exporter\", instance=~\"$instance\"})",
          "legendFormat": "used",
          "refId": "A"
        }
      ],
      "fieldConfig": {
        "defaults": {
          "unit": "percentunit",
          "min": 0,
          "max": 1,
          "color": { "mode": "palette-classic" }
        },
        "overrides": []
      },
      "options": {
        "tooltip": { "mode": "single", "sort": "none" },
        "legend": { "displayMode": "list", "placement": "bottom", "showLegend": true }
      }
    },
    {
      "id": 4,
      "title": "Memory Breakdown",
      "type": "timeseries",
      "gridPos": { "h": 8, "w": 12, "x": 12, "y": 8 },
      "datasource": { "type": "prometheus", "uid": "prometheus" },
      "targets": [
        {
          "datasource": { "type": "prometheus", "uid": "prometheus" },
          "expr": "node_memory_MemTotal_bytes{job=\"node_exporter\", instance=~\"$instance\"}",
          "legendFormat": "total",
          "refId": "A"
        },
        {
          "datasource": { "type": "prometheus", "uid": "prometheus" },
          "expr": "node_memory_MemAvailable_bytes{job=\"node_exporter\", instance=~\"$instance\"}",
          "legendFormat": "available",
          "refId": "B"
        },
        {
          "datasource": { "type": "prometheus", "uid": "prometheus" },
          "expr": "node_memory_Cached_bytes{job=\"node_exporter\", instance=~\"$instance\"} + node_memory_Buffers_bytes{job=\"node_exporter\", instance=~\"$instance\"}",
          "legendFormat": "cached+buffered",
          "refId": "C"
        }
      ],
      "fieldConfig": {
        "defaults": {
          "unit": "bytes",
          "min": 0,
          "color": { "mode": "palette-classic" }
        },
        "overrides": []
      },
      "options": {
        "tooltip": { "mode": "single", "sort": "none" },
        "legend": { "displayMode": "list", "placement": "bottom", "showLegend": true }
      }
    },
    {
      "id": 5,
      "title": "Disk IO Busy",
      "type": "timeseries",
      "gridPos": { "h": 8, "w": 12, "x": 0, "y": 16 },
      "datasource": { "type": "prometheus", "uid": "prometheus" },
      "targets": [
        {
          "datasource": { "type": "prometheus", "uid": "prometheus" },
          "expr": "rate(node_disk_io_time_seconds_total{job=\"node_exporter\", instance=~\"$instance\", device!~\"loop.*\"}[5m])",
          "legendFormat": "{{device}}",
          "refId": "A"
        }
      ],
      "fieldConfig": {
        "defaults": {
          "unit": "percentunit",
          "min": 0,
          "max": 1,
          "color": { "mode": "palette-classic" }
        },
        "overrides": []
      },
      "options": {
        "tooltip": { "mode": "multi", "sort": "none" },
        "legend": { "displayMode": "list", "placement": "bottom", "showLegend": true }
      }
    },
    {
      "id": 6,
      "title": "Filesystem Used",
      "type": "bargauge",
      "gridPos": { "h": 8, "w": 12, "x": 12, "y": 16 },
      "datasource": { "type": "prometheus", "uid": "prometheus" },
      "targets": [
        {
          "datasource": { "type": "prometheus", "uid": "prometheus" },
          "expr": "1 - node_filesystem_avail_bytes{job=\"node_exporter\", instance=~\"$instance\", fstype!~\"tmpfs|devtmpfs|overlay|squashfs\", mountpoint!~\"/run.*|/sys.*|/proc.*|/dev.*|/snap.*\"} / node_filesystem_size_bytes{job=\"node_exporter\", instance=~\"$instance\", fstype!~\"tmpfs|devtmpfs|overlay|squashfs\", mountpoint!~\"/run.*|/sys.*|/proc.*|/dev.*|/snap.*\"}",
          "legendFormat": "{{mountpoint}}",
          "refId": "A",
          "instant": true
        }
      ],
      "fieldConfig": {
        "defaults": {
          "unit": "percentunit",
          "min": 0,
          "max": 1,
          "color": {
            "mode": "thresholds"
          },
          "thresholds": {
            "mode": "absolute",
            "steps": [
              { "color": "green", "value": null },
              { "color": "yellow", "value": 0.75 },
              { "color": "red", "value": 0.90 }
            ]
          }
        },
        "overrides": []
      },
      "options": {
        "orientation": "horizontal",
        "reduceOptions": { "calcs": ["lastNotNull"] },
        "displayMode": "gradient",
        "showUnfilled": true
      }
    },
    {
      "id": 7,
      "title": "Network Receive",
      "type": "timeseries",
      "gridPos": { "h": 8, "w": 12, "x": 0, "y": 24 },
      "datasource": { "type": "prometheus", "uid": "prometheus" },
      "targets": [
        {
          "datasource": { "type": "prometheus", "uid": "prometheus" },
          "expr": "sum without(device)(rate(node_network_receive_bytes_total{job=\"node_exporter\", instance=~\"$instance\", device!=\"lo\"}[5m]))",
          "legendFormat": "rx",
          "refId": "A"
        }
      ],
      "fieldConfig": {
        "defaults": {
          "unit": "binBps",
          "min": 0,
          "color": { "mode": "palette-classic" }
        },
        "overrides": []
      },
      "options": {
        "tooltip": { "mode": "single", "sort": "none" },
        "legend": { "displayMode": "list", "placement": "bottom", "showLegend": true }
      }
    },
    {
      "id": 8,
      "title": "Network Transmit",
      "type": "timeseries",
      "gridPos": { "h": 8, "w": 12, "x": 12, "y": 24 },
      "datasource": { "type": "prometheus", "uid": "prometheus" },
      "targets": [
        {
          "datasource": { "type": "prometheus", "uid": "prometheus" },
          "expr": "sum without(device)(rate(node_network_transmit_bytes_total{job=\"node_exporter\", instance=~\"$instance\", device!=\"lo\"}[5m]))",
          "legendFormat": "tx",
          "refId": "A"
        }
      ],
      "fieldConfig": {
        "defaults": {
          "unit": "binBps",
          "min": 0,
          "color": { "mode": "palette-classic" }
        },
        "overrides": []
      },
      "options": {
        "tooltip": { "mode": "single", "sort": "none" },
        "legend": { "displayMode": "list", "placement": "bottom", "showLegend": true }
      }
    }
  ]
}
